{
	"parent": "block/block",
    "textures": {
        "0": "minecraft:blocks/glass_cyan"
    },
    "elements": [
        {
            "name": "Base",
            "from": [ 0.0, 0.0, 0.0 ], 
            "to": [ 16.0, 7.0, 16.0 ], 
            "faces": {
                "north": { "texture": "#-1", "uv": [ 0.0, 0.0, 16.0, 7.0 ] },
                "east": { "texture": "#-1", "uv": [ 0.0, 0.0, 16.0, 7.0 ] },
                "south": { "texture": "#-1", "uv": [ 0.0, 0.0, 16.0, 7.0 ] },
                "west": { "texture": "#-1", "uv": [ 0.0, 0.0, 16.0, 7.0 ] },
                "up": { "texture": "#-1", "uv": [ 0.0, 0.0, 16.0, 16.0 ] },
                "down": { "texture": "#-1", "uv": [ 0.0, 0.0, 16.0, 16.0 ] }
            }
        },
        {
            "name": "Platform",
            "from": [ 2.5, 7.0, 2.5 ], 
            "to": [ 13.0, 8.0, 13.0 ], 
            "faces": {
                "north": { "texture": "#-1", "uv": [ 0.0, 0.0, 10.5, 1.0 ] },
                "east": { "texture": "#-1", "uv": [ 0.0, 0.0, 10.5, 1.0 ] },
                "south": { "texture": "#-1", "uv": [ 0.0, 0.0, 10.5, 1.0 ] },
                "west": { "texture": "#-1", "uv": [ 0.0, 0.0, 10.5, 1.0 ] },
                "up": { "texture": "#-1", "uv": [ 0.0, 0.0, 10.5, 10.5 ] },
                "down": { "texture": "#-1", "uv": [ 0.0, 0.0, 10.5, 10.5 ] }
            }
        },
        {
            "name": "Monacle Post",
            "from": [ 2.0, 7.0, 2.0 ], 
            "to": [ 3.0, 13.0, 3.0 ], 
            "faces": {
                "north": { "texture": "#-1", "uv": [ 0.0, 0.0, 1.0, 6.0 ] },
                "east": { "texture": "#-1", "uv": [ 0.0, 0.0, 1.0, 6.0 ] },
                "south": { "texture": "#-1", "uv": [ 0.0, 0.0, 1.0, 6.0 ] },
                "west": { "texture": "#-1", "uv": [ 0.0, 0.0, 1.0, 6.0 ] },
                "up": { "texture": "#-1", "uv": [ 0.0, 0.0, 1.0, 1.0 ] },
                "down": { "texture": "#-1", "uv": [ 0.0, 0.0, 1.0, 1.0 ] }
            }
        },
        {
            "name": "North Part 1",
            "from": [ 7.0, 12.0, 2.0 ], 
            "to": [ 9.0, 13.0, 3.0 ], 
            "faces": {
                "north": { "texture": "#-1", "uv": [ 0.0, 0.0, 2.0, 1.0 ] },
                "east": { "texture": "#-1", "uv": [ 0.0, 0.0, 1.0, 1.0 ] },
                "south": { "texture": "#-1", "uv": [ 0.0, 0.0, 2.0, 1.0 ] },
                "west": { "texture": "#-1", "uv": [ 0.0, 0.0, 1.0, 1.0 ] },
                "up": { "texture": "#-1", "uv": [ 0.0, 0.0, 2.0, 1.0 ] },
                "down": { "texture": "#-1", "uv": [ 0.0, 0.0, 2.0, 1.0 ] }
            }
        },
        {
            "name": "South Part",
            "from": [ 7.0, 12.0, 12.0 ], 
            "to": [ 9.0, 13.0, 13.0 ], 
            "faces": {
                "north": { "texture": "#-1", "uv": [ 0.0, 0.0, 2.0, 1.0 ] },
                "east": { "texture": "#-1", "uv": [ 0.0, 0.0, 1.0, 1.0 ] },
                "south": { "texture": "#-1", "uv": [ 0.0, 0.0, 2.0, 1.0 ] },
                "west": { "texture": "#-1", "uv": [ 0.0, 0.0, 1.0, 1.0 ] },
                "up": { "texture": "#-1", "uv": [ 0.0, 0.0, 2.0, 1.0 ] },
                "down": { "texture": "#-1", "uv": [ 0.0, 0.0, 2.0, 1.0 ] }
            }
        },
        {
            "name": "East Part",
            "from": [ 12.0, 12.0, 7.0 ], 
            "to": [ 13.0, 13.0, 9.0 ], 
            "faces": {
                "north": { "texture": "#-1", "uv": [ 0.0, 0.0, 1.0, 1.0 ] },
                "east": { "texture": "#-1", "uv": [ 0.0, 0.0, 2.0, 1.0 ] },
                "south": { "texture": "#-1", "uv": [ 0.0, 0.0, 1.0, 1.0 ] },
                "west": { "texture": "#-1", "uv": [ 0.0, 0.0, 2.0, 1.0 ] },
                "up": { "texture": "#-1", "uv": [ 0.0, 0.0, 1.0, 2.0 ] },
                "down": { "texture": "#-1", "uv": [ 0.0, 0.0, 1.0, 2.0 ] }
            }
        },
        {
            "name": "West Part",
            "from": [ 2.0, 12.0, 7.0 ], 
            "to": [ 3.0, 13.0, 9.0 ], 
            "faces": {
                "north": { "texture": "#-1", "uv": [ 0.0, 0.0, 1.0, 1.0 ] },
                "east": { "texture": "#-1", "uv": [ 0.0, 0.0, 2.0, 1.0 ] },
                "south": { "texture": "#-1", "uv": [ 0.0, 0.0, 1.0, 1.0 ] },
                "west": { "texture": "#-1", "uv": [ 0.0, 0.0, 2.0, 1.0 ] },
                "up": { "texture": "#-1", "uv": [ 0.0, 0.0, 1.0, 2.0 ] },
                "down": { "texture": "#-1", "uv": [ 0.0, 0.0, 1.0, 2.0 ] }
            }
        },
        {
            "name": "North Part 0",
            "from": [ 2.5, 12.2, 2.5 ], 
            "to": [ 7.0, 12.7, 3.0 ], 
            "faces": {
                "north": { "texture": "#-1", "uv": [ 0.0, 0.0, 4.5, 0.5 ] },
                "east": { "texture": "#-1", "uv": [ 0.0, 0.0, 0.5, 0.5 ] },
                "south": { "texture": "#-1", "uv": [ 0.0, 0.0, 4.5, 0.5 ] },
                "west": { "texture": "#-1", "uv": [ 0.0, 0.0, 0.5, 0.5 ] },
                "up": { "texture": "#-1", "uv": [ 0.0, 0.0, 4.5, 0.5 ] },
                "down": { "texture": "#-1", "uv": [ 0.0, 0.0, 4.5, 0.5 ] }
            }
        },
        {
            "name": "West Part 0",
            "from": [ 2.5, 12.2, 2.5 ], 
            "to": [ 3.0, 12.7, 7.0 ], 
            "faces": {
                "north": { "texture": "#-1", "uv": [ 0.0, 0.0, 0.5, 0.5 ] },
                "east": { "texture": "#-1", "uv": [ 0.0, 0.0, 4.5, 0.5 ] },
                "south": { "texture": "#-1", "uv": [ 0.0, 0.0, 0.5, 0.5 ] },
                "west": { "texture": "#-1", "uv": [ 0.0, 0.0, 4.5, 0.5 ] },
                "up": { "texture": "#-1", "uv": [ 0.0, 0.0, 0.5, 4.5 ] },
                "down": { "texture": "#-1", "uv": [ 0.0, 0.0, 0.5, 4.5 ] }
            }
        },
        {
            "name": "Monacle",
            "from": [ 3.0, 12.3, 3.0 ], 
            "to": [ 12.0, 12.5, 12.0 ], 
            "faces": {
                "north": { "texture": "#0", "uv": [ 0.0, 0.0, 9.0, 0.2 ] },
                "east": { "texture": "#0", "uv": [ 0.0, 0.0, 9.0, 0.2 ] },
                "south": { "texture": "#0", "uv": [ 0.0, 0.0, 9.0, 0.2 ] },
                "west": { "texture": "#0", "uv": [ 0.0, 0.0, 9.0, 0.2 ] },
                "up": { "texture": "#0", "uv": [ 3.0, 3.0, 12.0, 12.0 ] },
                "down": { "texture": "#0", "uv": [ 3.0, 3.0, 12.0, 12.0 ] }
            }
        }
    ]
}